odoo9_addon_geoengine_partner-9.0.1.0.0-py2.7-nspkg.pth
odoo9_addon_geoengine_partner-9.0.1.0.0.dist-info/DESCRIPTION.rst
odoo9_addon_geoengine_partner-9.0.1.0.0.dist-info/METADATA
odoo9_addon_geoengine_partner-9.0.1.0.0.dist-info/RECORD
odoo9_addon_geoengine_partner-9.0.1.0.0.dist-info/WHEEL
odoo9_addon_geoengine_partner-9.0.1.0.0.dist-info/metadata.json
odoo9_addon_geoengine_partner-9.0.1.0.0.dist-info/namespace_packages.txt
odoo9_addon_geoengine_partner-9.0.1.0.0.dist-info/top_level.txt
odoo_addons/geoengine_partner/README.rst
odoo_addons/geoengine_partner/__init__.py
odoo_addons/geoengine_partner/__openerp__.py
odoo_addons/geoengine_partner/models/__init__.py
odoo_addons/geoengine_partner/models/partner.py
odoo_addons/geoengine_partner/static/description/icon.png
odoo_addons/geoengine_partner/views/partner.xml
